AUTHORS
ChangeLog
README.md
requirements.txt
setup.cfg
setup.py
etc/openlab.conf
openlabcmd/__init__.py
openlabcmd/cli.py
openlabcmd/constants.py
openlabcmd/exceptions.py
openlabcmd/hint.py
openlabcmd/node.py
openlabcmd/repo.py
openlabcmd/service.py
openlabcmd/utils.py
openlabcmd/zk.py
openlabcmd.egg-info/PKG-INFO
openlabcmd.egg-info/SOURCES.txt
openlabcmd.egg-info/dependency_links.txt
openlabcmd.egg-info/entry_points.txt
openlabcmd.egg-info/not-zip-safe
openlabcmd.egg-info/pbr.json
openlabcmd.egg-info/requires.txt
openlabcmd.egg-info/top_level.txt
openlabcmd/plugins/__init__.py
openlabcmd/plugins/base.py
openlabcmd/plugins/recover.py
openlabcmd/plugins/jobs/__init__.py
openlabcmd/plugins/jobs/image.py
openlabcmd/plugins/nodepool/__init__.py
openlabcmd/plugins/nodepool/auth.py
openlabcmd/plugins/nodepool/flavor.py
openlabcmd/plugins/nodepool/network.py
openlabcmd/plugins/nodepool/orphanresource.py
openlabcmd/plugins/nodepool/quota.py
openlabcmd/plugins/nodepool/securitygroup.py