Metadata-Version: 2.1
Name: openlabcmd
Version: 1.8.3
Summary: The command line tool for OpenLab
Home-page: https://openlabtesting.org/
Author: OpenLab Team
License: UNKNOWN
Platform: UNKNOWN
Classifier: Intended Audience :: Information Technology
Classifier: Intended Audience :: System Administrators
Classifier: License :: OSI Approved :: Apache Software License
Classifier: Operating System :: POSIX :: Linux
Classifier: Programming Language :: Python
Classifier: Programming Language :: Python :: 3
Classifier: Programming Language :: Python :: 3.5
Requires-Python: >=3.5
